[
  {
    "numerKRS": "7489791776",
    "nip": "8621750801",
    "regon": "334272038",
    "nazwa": "Baltic Med Supply Group spółka akcyjna",
    "nazwaSkrocona": "Baltic Med Supply Group",
    "formaPrawna": "spółka akcyjna",
    "status": "W TRAKCIE LIKWIDACJI",
    "dataRejestracji": "2019-09-03",
    "siedziba": "Bydgoszcz",
    "adres": "ulica Bałtycka 51/3, 85-707 Bydgoszcz",
    "pkd": "62.01.Z",
    "kapitalZakladowy": "100000 PLN",
    "reprezentacja": "dwóch członków zarządu łącznie"
  },
  {
    "numerKRS": "5179937810",
    "nip": "4869996988",
    "regon": "539128788",
    "nazwa": "Nebula Analytics Solutions SP Z O O",
    "nazwaSkrocona": "Nebula Analytics Solutions",
    "formaPrawna": "SP Z O O",
    "status": "AKTYWNY",
    "dataRejestracji": "2022-06-16",
    "siedziba": "Gdynia",
    "adres": "ul Portowa 67, 81-350 Gdynia",
    "pkd": "64.19.Z",
    "kapitalZakladowy": "10000 PLN",
    "reprezentacja": "dwóch członków zarządu łącznie"
  },
  {
    "numerKRS": "3972833912",
    "nip": "8809832210",
    "regon": "187062932",
    "nazwa": "Altair iFnance Group SA",
    "nazwaSkrocona": "Altair Finance Group",
    "formaPrawna": "SA",
    "status": "AKTYWNY",
    "dataRejestracji": "2019-12-17",
    "siedziba": "Katowice",
    "adres": "40-121 Katowice, ul Chorzowska 98 m.6",
    "pkd": "62.01.Z",
    "kapitalZakladowy": "100000 PLN",
    "reprezentacja": "dwóch członków zarządu łącznie"
  },
  {
    "numerKRS": "8453198074",
    "nip": "1003076205",
    "regon": "682354695",
    "nazwa": "Baltic Med Supply Holding sp. z o.o.",
    "nazwaSkrocona": "Baltic Med Supply Holding",
    "formaPrawna": "sp. z o.o.",
    "status": "W TRAKCIE LIKWIDACJI",
    "dataRejestracji": "2024-08-27",
    "siedziba": "Poznań",
    "adres": "ul. Głogowska 49, 60-126 Poznań",
    "pkd": "47.91.Z",
    "kapitalZakladowy": "5000 PLN",
    "reprezentacja": "likwidator samodzielnie"
  },
  {
    "numerKRS": "4078516994",
    "nip": "6683482689",
    "regon": "970890583",
    "nazwa": "Baltic Med Supply Tech spółka akcyjna",
    "nazwaSkrocona": "BALTIC MED SUPPLY TECH",
    "formaPrawna": "spółka akcyjna",
    "status": "AKTYWNY",
    "dataRejestracji": "2019-10-15",
    "siedziba": "Gdynia",
    "adres": "81-350 Gdynia, ul Portowa 77 m.23",
    "pkd": "62.02.Z",
    "kapitalZakladowy": "1200000 PLN",
    "reprezentacja": "każdy członek zarządu samodzielnie"
  },
  {
    "numerKRS": "5217558517",
    "nip": "2118824199",
    "regon": "774127469",
    "nazwa": "Baltic Med Supply Solutions SA",
    "nazwaSkrocona": "Baltic Med Supply Solutions",
    "formaPrawna": "SA",
    "status": "AKTYWNY",
    "dataRejestracji": "2024-09-05",
    "siedziba": "Kraków",
    "adres": "ul. Konopnickiej 4, 30-302 Kraków",
    "pkd": "63.11.Z",
    "kapitalZakladowy": "10000 PLN",
    "reprezentacja": "każdy członek zarządu samodzielnie"
  },
  {
    "numerKRS": "7282895400",
    "nip": "1261685071",
    "regon": "178822473",
    "nazwa": "Orbis Retail Solutions Group S.A.",
    "nazwaSkrocona": "Orbis Retail Solutions Group",
    "formaPrawna": "S.A.",
    "status": "AKTYWNY",
    "dataRejestracji": "2019-07-19",
    "siedziba": "Kraków",
    "adres": "30-302 Kraków, ul Konopnickiej 71 m.15",
    "pkd": "64.19.Z",
    "kapitalZakladowy": "5000 PLN",
    "reprezentacja": "każdy członek zarządu samodzielnie"
  },
  {
    "numerKRS": "5294471619",
    "nip": "0450258963",
    "regon": "827348131",
    "nazwa": "Amber Tech Solutions sp z oo",
    "nazwaSkrocona": "Amber Tech Solutions",
    "formaPrawna": "sp z oo",
    "status": "W TRAKCIE LIKWIDACJI",
    "dataRejestracji": "2022-05-18",
    "siedziba": "Rzeszów",
    "adres": "ul 3 Maja 134, 35-001 Rzeszów",
    "pkd": "46.46.Z",
    "kapitalZakladowy": "1200000 PLN",
    "reprezentacja": "dwóch członków zarządu łącznie"
  },
  {
    "numerKRS": "1562392090",
    "nip": "1311178619",
    "regon": "855107409",
    "nazwa": "Vistula Data Hub Servcies Sp. z o.o.",
    "nazwaSkrocona": "Vistula Data Hub Services",
    "formaPrawna": "Sp. z o.o.",
    "status": "AKTYWNY",
    "dataRejestracji": "2024-01-22",
    "siedziba": "Wrocław",
    "adres": "ulica Kazimierza Wielkiego 71/13, 50-101 Wrocław",
    "pkd": "46.46.Z",
    "kapitalZakladowy": "10000 PLN",
    "reprezentacja": "likwidator samodzielnie"
  },
  {
    "numerKRS": "0260151532",
    "nip": "0717327980",
    "regon": "594795074",
    "nazwa": "Vistula Data Hub Solutions spółka z ograniczoną odpowiedzialnością",
    "nazwaSkrocona": "VISTULA DATA HUB SOLUTIONS",
    "formaPrawna": "spółka z ograniczoną odpowiedzialnością",
    "status": "W TRAKCIE LIKWIDACJI",
    "dataRejestracji": "2018-04-22",
    "siedziba": "Bydgoszcz",
    "adres": "ul. Bałtycka 47, 85-707 Bydgoszcz",
    "pkd": "62.02.Z",
    "kapitalZakladowy": "5000 PLN",
    "reprezentacja": "dwóch członków zarządu łącznie"
  },
  {
    "numerKRS": "1184913599",
    "nip": "0561006799",
    "regon": "285535952",
    "nazwa": "Helix Retail Solutions Sp. z o.o.",
    "nazwaSkrocona": "HELIX RETAIL SOLUTIONS",
    "formaPrawna": "Sp. z o.o.",
    "status": "AKTYWNY",
    "dataRejestracji": "2018-01-13",
    "siedziba": "Warszawa",
    "adres": "00-810 Warszawa, Srebrna 55",
    "pkd": "62.01.Z",
    "kapitalZakladowy": "100000 PLN",
    "reprezentacja": "każdy członek zarządu samodzielnie"
  },
  {
    "numerKRS": "2902923345",
    "nip": "3088684302",
    "regon": "110090605",
    "nazwa": "Altair Finanec Polska Sp. z o.o.",
    "nazwaSkrocona": "Altair Finance Polska",
    "formaPrawna": "Sp. z o.o.",
    "status": "AKTYWNY",
    "dataRejestracji": "2018-05-22",
    "siedziba": "Poznań",
    "adres": "60-126 Poznań, ul Głogowska 34 m.6",
    "pkd": "62.01.Z",
    "kapitalZakladowy": "50000 PLN",
    "reprezentacja": "likwidator samodzielnie"
  },
  {
    "numerKRS": "0275582147",
    "nip": "2380236219",
    "regon": "709207115",
    "nazwa": "Nova Systems Group sp. z o.o.",
    "nazwaSkrocona": "Nova Systems Group",
    "formaPrawna": "sp. z o.o.",
    "status": "AKTYWNY",
    "dataRejestracji": "2025-12-01",
    "siedziba": "Poznań",
    "adres": "ul Głogowska 43, 60-126 Poznań",
    "pkd": "47.91.Z",
    "kapitalZakladowy": "1200000 PLN",
    "reprezentacja": "każdy członek zarządu samodzielnie"
  },
  {
    "numerKRS": "6880053789",
    "nip": "2845401822",
    "regon": "318692897",
    "nazwa": "Polaris Medical Group spółka z ograniczoną odpowiedzialnością",
    "nazwaSkrocona": "Polarsi Medical Group",
    "formaPrawna": "spółka z ograniczoną odpowiedzialnością",
    "status": "AKTYWNY",
    "dataRejestracji": "2022-09-05",
    "siedziba": "Rzeszów",
    "adres": "ulica 3 Maja 81/15, 35-001 Rzeszów",
    "pkd": "46.46.Z",
    "kapitalZakladowy": "10000 PLN",
    "reprezentacja": "likwidator samodzielnie"
  },
  {
    "numerKRS": "0202030423",
    "nip": "3028165064",
    "regon": "227752135",
    "nazwa": "Vistula Data Hub Solutions sp. z o.o.",
    "nazwaSkrocona": "Vistula Data Hub Solutions",
    "formaPrawna": "sp. z o.o.",
    "status": "AKTYWNY",
    "dataRejestracji": "2021-02-26",
    "siedziba": "Katowice",
    "adres": "ul. Chorzowska 29, 40-121 Katowice",
    "pkd": "47.91.Z",
    "kapitalZakladowy": "10000 PLN",
    "reprezentacja": "likwidator samodzielnie"
  },
  {
    "numerKRS": "5667063621",
    "nip": "4407663493",
    "regon": "986550494",
    "nazwa": "Helix Retail Polska SP Z O O",
    "nazwaSkrocona": "HELIX RETAIL POLSKA",
    "formaPrawna": "SP Z O O",
    "status": "W TRAKCIE LIKWIDACJI",
    "dataRejestracji": "2024-03-15",
    "siedziba": "Lublin",
    "adres": "ul. Topolowa 108, 20-819 Lublin",
    "pkd": "46.46.Z",
    "kapitalZakladowy": "10000 PLN",
    "reprezentacja": "dwóch członków zarządu łącznie"
  },
  {
    "numerKRS": "8087991962",
    "nip": "8532472505",
    "regon": "341996433",
    "nazwa": "Altair Finance Tech SP Z O O",
    "nazwaSkrocona": "Altair Finance Tech",
    "formaPrawna": "SP Z O O",
    "status": "W TRAKCIE LIKWIDACJI",
    "dataRejestracji": "2022-12-25",
    "siedziba": "Gdynia",
    "adres": "ulica Portowa 168/11, 81-350 Gdynia",
    "pkd": "47.91.Z",
    "kapitalZakladowy": "10000 PLN",
    "reprezentacja": "dwóch członków zarządu łącznie"
  },
  {
    "numerKRS": "4508095948",
    "nip": "6647213074",
    "regon": "152692559",
    "nazwa": "Altair Finance Group Sp. z o.o.",
    "nazwaSkrocona": "Altair Finance Group",
    "formaPrawna": "Sp. z o.o.",
    "status": "AKTYWNY",
    "dataRejestracji": "2021-02-22",
    "siedziba": "Lublin",
    "adres": "ul. Topolowa 111, 20-819 Lublin",
    "pkd": "62.02.Z",
    "kapitalZakladowy": "1200000 PLN",
    "reprezentacja": "likwidator samodzielnie"
  },
  {
    "numerKRS": "4268744701",
    "nip": "7772966563",
    "regon": "732086523",
    "nazwa": "Nova Systems Holding SA",
    "nazwaSkrocona": "NOVA SYSTEMS HOLDING",
    "formaPrawna": "SA",
    "status": "AKTYWNY",
    "dataRejestracji": "2021-02-14",
    "siedziba": "Katowice",
    "adres": "ul. Chorzowska 72, 40-121 Katowice",
    "pkd": "63.11.Z",
    "kapitalZakladowy": "50000 PLN",
    "reprezentacja": "każdy członek zarządu samodzielnie"
  },
  {
    "numerKRS": "0929735259",
    "nip": "3899204573",
    "regon": "533222739",
    "nazwa": "Orbis Retail Solutions Solutions sp. z o.o.",
    "nazwaSkrocona": "ORBIS RETAIL SOLUTIONS SOLUTIONS",
    "formaPrawna": "sp. z o.o.",
    "status": "AKTYWNY",
    "dataRejestracji": "2023-01-16",
    "siedziba": "Rzeszów",
    "adres": "35-001 Rzeszów, 3 Maja 89",
    "pkd": "62.02.Z",
    "kapitalZakladowy": "5000 PLN",
    "reprezentacja": "likwidator samodzielnie"
  },
  {
    "numerKRS": "1583882176",
    "nip": "2233222801",
    "regon": "484673574",
    "nazwa": "Nebula Analytics Services sp z oo",
    "nazwaSkrocona": "NEBULA ANALYTICS SERVICES",
    "formaPrawna": "sp z oo",
    "status": "W TRAKCIE LIKWIDACJI",
    "dataRejestracji": "2020-12-27",
    "siedziba": "Olsztyn",
    "adres": "ul Jarzębinowa 98, 10-687 Olsztyn",
    "pkd": "64.19.Z",
    "kapitalZakladowy": "10000 PLN",
    "reprezentacja": "każdy członek zarządu samodzielnie"
  },
  {
    "numerKRS": "8046741307",
    "nip": "1362608463",
    "regon": "538418520",
    "nazwa": "Nova Systems Polska spółka akcyjna",
    "nazwaSkrocona": "NOVA SYSTEMS POLSKA",
    "formaPrawna": "spółka akcyjna",
    "status": "AKTYWNY",
    "dataRejestracji": "2024-05-01",
    "siedziba": "Olsztyn",
    "adres": "ulica Jarzębinowa 163/16, 10-687 Olsztyn",
    "pkd": "64.19.Z",
    "kapitalZakladowy": "5000 PLN",
    "reprezentacja": "likwidator samodzielnie"
  },
  {
    "numerKRS": "0197121241",
    "nip": "7609873126",
    "regon": "393696789",
    "nazwa": "OrbisR etail Solutions Services SA",
    "nazwaSkrocona": "ORBIS RETAIL SOLUTIONS SERVICES",
    "formaPrawna": "SA",
    "status": "AKTYWNY",
    "dataRejestracji": "2022-04-01",
    "siedziba": "Warszawa",
    "adres": "ul Srebrna 36, 00-810 Warszawa",
    "pkd": "64.19.Z",
    "kapitalZakladowy": "1200000 PLN",
    "reprezentacja": "likwidator samodzielnie"
  },
  {
    "numerKRS": "7000268764",
    "nip": "7416365604",
    "regon": "486764979",
    "nazwa": "Altair Finance Solutions S.p z o.o.",
    "nazwaSkrocona": "ALTAIR FINANCE SOLUTIONS",
    "formaPrawna": "Sp. z o.o.",
    "status": "W TRAKCIE LIKWIDACJI",
    "dataRejestracji": "2021-08-07",
    "siedziba": "Gdynia",
    "adres": "ul. Portowa 125/9, 81-350 Gdynia",
    "pkd": "63.11.Z",
    "kapitalZakladowy": "100000 PLN",
    "reprezentacja": "dwóch członków zarządu łącznie"
  },
  {
    "numerKRS": "0255128276",
    "nip": "9895965466",
    "regon": "364315948",
    "nazwa": "Nebula Analytics Tech spz  oo",
    "nazwaSkrocona": "Nebula Analytics Tech",
    "formaPrawna": "sp z oo",
    "status": "W TRAKCIE LIKWIDACJI",
    "dataRejestracji": "2020-03-08",
    "siedziba": "Kraków",
    "adres": "ul. Konopnickiej 58, 30-302 Kraków",
    "pkd": "63.11.Z",
    "kapitalZakladowy": "50000 PLN",
    "reprezentacja": "likwidator samodzielnie"
  },
  {
    "numerKRS": "2170754853",
    "nip": "3004496461",
    "regon": "465579220",
    "nazwa": "Nebula Analytics Solutions spółka z ograniczoną odpowiedzialnością",
    "nazwaSkrocona": "Nebula Analytics Solutions",
    "formaPrawna": "spółka z ograniczoną odpowiedzialnością",
    "status": "W TRAKCIE LIKWIDACJI",
    "dataRejestracji": "2021-02-09",
    "siedziba": "Olsztyn",
    "adres": "ul Jarzębinowa 41, 10-687 Olsztyn",
    "pkd": "47.91.Z",
    "kapitalZakladowy": "1200000 PLN",
    "reprezentacja": "dwóch członków zarządu łącznie"
  },
  {
    "numerKRS": "2033474246",
    "nip": "6800852946",
    "regon": "310437968",
    "nazwa": "Orbis Retail Solutions Group spółka akcyjna",
    "nazwaSkrocona": "Orbis Retail Solutions Group",
    "formaPrawna": "spółka akcyjna",
    "status": "AKTYWNY",
    "dataRejestracji": "2025-08-10",
    "siedziba": "Warszawa",
    "adres": "ul. Srebrna 53, 00-810 Warszawa",
    "pkd": "62.01.Z",
    "kapitalZakladowy": "50000 PLN",
    "reprezentacja": "każdy członek zarządu samodzielnie"
  },
  {
    "numerKRS": "2332829302",
    "nip": "3033467711",
    "regon": "025691330",
    "nazwa": "Meridian Trade Holding Sp. z o.o.",
    "nazwaSkrocona": "MERIDIAN TRADE HOLDING",
    "formaPrawna": "Sp. z o.o.",
    "status": "AKTYWNY",
    "dataRejestracji": "2020-04-01",
    "siedziba": "Katowice",
    "adres": "ul. Chorzowska 157/14, 40-121 Katowice",
    "pkd": "47.91.Z",
    "kapitalZakladowy": "10000 PLN",
    "reprezentacja": "każdy członek zarządu samodzielnie"
  },
  {
    "numerKRS": "4871775461",
    "nip": "8727258122",
    "regon": "992406583",
    "nazwa": "Vistula Data Hub Polska sp z oo",
    "nazwaSkrocona": "Vistula Data Hbu Polska",
    "formaPrawna": "sp z oo",
    "status": "AKTYWNY",
    "dataRejestracji": "2021-12-12",
    "siedziba": "Bydgoszcz",
    "adres": "ul Bałtycka 75, 85-707 Bydgoszcz",
    "pkd": "63.11.Z",
    "kapitalZakladowy": "100000 PLN",
    "reprezentacja": "likwidator samodzielnie"
  },
  {
    "numerKRS": "7122276433",
    "nip": "1626549633",
    "regon": "872205422",
    "nazwa": "Vistula Data Hub Group spółka z ogarniczoną odpowiedzialnością",
    "nazwaSkrocona": "Vistula Data Hub Group",
    "formaPrawna": "spółka z ograniczoną odpowiedzialnością",
    "status": "AKTYWNY",
    "dataRejestracji": "2022-05-15",
    "siedziba": "Rzeszów",
    "adres": "ul. 3 Maja 159/23, 35-001 Rzeszów",
    "pkd": "47.91.Z",
    "kapitalZakladowy": "1200000 PLN",
    "reprezentacja": "likwidator samodzielnie"
  },
  {
    "numerKRS": "5377492663",
    "nip": "7522592061",
    "regon": "295634277",
    "nazwa": "Helix Retail Tech SP Z O O",
    "nazwaSkrocona": "Helix Retail Tech",
    "formaPrawna": "SP Z O O",
    "status": "W TRAKCIE LIKWIDACJI",
    "dataRejestracji": "2023-10-24",
    "siedziba": "Gdynia",
    "adres": "ul. Portowa 158/25, 81-350 Gdynia",
    "pkd": "46.46.Z",
    "kapitalZakladowy": "1200000 PLN",
    "reprezentacja": "dwóch członków zarządu łącznie"
  },
  {
    "numerKRS": "6294206615",
    "nip": "1380049832",
    "regon": "498085133",
    "nazwa": "Nova Systems Services sp. z o.o.",
    "nazwaSkrocona": "Nova Systems Services",
    "formaPrawna": "sp. z o.o.",
    "status": "W TRAKCIE LIKWIDACJI",
    "dataRejestracji": "2023-05-18",
    "siedziba": "Rzeszów",
    "adres": "ul 3 Maja 103, 35-001 Rzeszów",
    "pkd": "62.02.Z",
    "kapitalZakladowy": "100000 PLN",
    "reprezentacja": "dwóch członków zarządu łącznie"
  },
  {
    "numerKRS": "4196234219",
    "nip": "1042948314",
    "regon": "262213204",
    "nazwa": "Meridian Trade Tech sp z oo",
    "nazwaSkrocona": "Meridian Trade Tech",
    "formaPrawna": "sp z oo",
    "status": "W TRAKCIE LIKWIDACJI",
    "dataRejestracji": "2019-02-16",
    "siedziba": "Olsztyn",
    "adres": "ulica Jarzębinowa 81/25, 10-687 Olsztyn",
    "pkd": "62.01.Z",
    "kapitalZakladowy": "10000 PLN",
    "reprezentacja": "dwóch członków zarządu łącznie"
  },
  {
    "numerKRS": "0005328538",
    "nip": "3838058269",
    "regon": "631050524",
    "nazwa": "Meridian Trade Services sp. z o.o.",
    "nazwaSkrocona": "Meridian Tarde Services",
    "formaPrawna": "sp. z o.o.",
    "status": "AKTYWNY",
    "dataRejestracji": "2024-03-13",
    "siedziba": "Katowice",
    "adres": "40-121 Katowice, Chorzowska 6",
    "pkd": "62.02.Z",
    "kapitalZakladowy": "10000 PLN",
    "reprezentacja": "dwóch członków zarządu łącznie"
  },
  {
    "numerKRS": "5279187506",
    "nip": "0881431927",
    "regon": "776106592",
    "nazwa": "Helix Retail Solutions sp. z o.o.",
    "nazwaSkrocona": "Helix Retail Solutions",
    "formaPrawna": "sp. z o.o.",
    "status": "AKTYWNY",
    "dataRejestracji": "2019-03-11",
    "siedziba": "Rzeszów",
    "adres": "35-001 Rzeszów, 3 Maja 40",
    "pkd": "46.46.Z",
    "kapitalZakladowy": "50000 PLN",
    "reprezentacja": "likwidator samodzielnie"
  },
  {
    "numerKRS": "7472966941",
    "nip": "9747485994",
    "regon": "799670808",
    "nazwa": "Orbis Retail Solutions Solutions spółka akcyjna",
    "nazwaSkrocona": "ORBIS RETAIL SOLUTIONS SOLUTIONS",
    "formaPrawna": "spółka akcyjna",
    "status": "AKTYWNY",
    "dataRejestracji": "2023-01-26",
    "siedziba": "Warszawa",
    "adres": "ulica Srebrna 114/29, 00-810 Warszawa",
    "pkd": "46.46.Z",
    "kapitalZakladowy": "1200000 PLN",
    "reprezentacja": "dwóch członków zarządu łącznie"
  },
  {
    "numerKRS": "5813088983",
    "nip": "7418563027",
    "regon": "057488399",
    "nazwa": "Helix Retail Group Sp. z o.o.",
    "nazwaSkrocona": "Helix Retail Group",
    "formaPrawna": "Sp. z o.o.",
    "status": "W TRAKCIE LIKWIDACJI",
    "dataRejestracji": "2023-12-13",
    "siedziba": "Katowice",
    "adres": "ulica Chorzowska 155/1, 40-121 Katowice",
    "pkd": "62.01.Z",
    "kapitalZakladowy": "5000 PLN",
    "reprezentacja": "likwidator samodzielnie"
  },
  {
    "numerKRS": "8701872600",
    "nip": "4429906745",
    "regon": "136510344",
    "nazwa": "Altair Finance Services spółka z ograniczoną odpowiedzialnością",
    "nazwaSkrocona": "ALTAIR FINANCE SERVICES",
    "formaPrawna": "spółka z ograniczoną odpowiedzialnością",
    "status": "AKTYWNY",
    "dataRejestracji": "2022-01-13",
    "siedziba": "Wrocław",
    "adres": "ul. Kazimierza Wielkiego 139/29, 50-101 Wrocław",
    "pkd": "46.46.Z",
    "kapitalZakladowy": "5000 PLN",
    "reprezentacja": "dwóch członków zarządu łącznie"
  },
  {
    "numerKRS": "4704747648",
    "nip": "1383507124",
    "regon": "455939652",
    "nazwa": "Nova Systems Group SA",
    "nazwaSkrocona": "Nova Systems Group",
    "formaPrawna": "SA",
    "status": "W TRAKCIE LIKWIDACJI",
    "dataRejestracji": "2023-09-11",
    "siedziba": "Lublin",
    "adres": "ul Topolowa 156, 20-819 Lublin",
    "pkd": "64.19.Z",
    "kapitalZakladowy": "50000 PLN",
    "reprezentacja": "likwidator samodzielnie"
  },
  {
    "numerKRS": "5080549147",
    "nip": "4784171594",
    "regon": "744735352",
    "nazwa": "Amber Tech Polska spółka z ograniczoną odpowiedzialnością",
    "nazwaSkrocona": "AMBER TECH POLSKA",
    "formaPrawna": "spółka z ograniczoną odpowiedzialnością",
    "status": "AKTYWNY",
    "dataRejestracji": "2021-01-11",
    "siedziba": "Katowice",
    "adres": "ul. Chorzowska 84, 40-121 Katowice",
    "pkd": "62.01.Z",
    "kapitalZakladowy": "1200000 PLN",
    "reprezentacja": "likwidator samodzielnie"
  },
  {
    "numerKRS": "2815278730",
    "nip": "7465353780",
    "regon": "486251521",
    "nazwa": "Nebula AnalyticsS olutions SP Z O O",
    "nazwaSkrocona": "Nebula Analytics Solutions",
    "formaPrawna": "SP Z O O",
    "status": "AKTYWNY",
    "dataRejestracji": "2022-06-02",
    "siedziba": "Katowice",
    "adres": "ulica Chorzowska 154/14, 40-121 Katowice",
    "pkd": "63.11.Z",
    "kapitalZakladowy": "1200000 PLN",
    "reprezentacja": "likwidator samodzielnie"
  },
  {
    "numerKRS": "6844246488",
    "nip": "5759582819",
    "regon": "499795728",
    "nazwa": "Baltic Med Supply Tech SP Z O O",
    "nazwaSkrocona": "Baltic Med Supply Tech",
    "formaPrawna": "SP Z O O",
    "status": "AKTYWNY",
    "dataRejestracji": "2025-03-17",
    "siedziba": "Olsztyn",
    "adres": "10-687 Olsztyn, ul Jarzębinowa 176 m.6",
    "pkd": "63.11.Z",
    "kapitalZakladowy": "5000 PLN",
    "reprezentacja": "każdy członek zarządu samodzielnie"
  },
  {
    "numerKRS": "9009921779",
    "nip": "3515880705",
    "regon": "055286693",
    "nazwa": "Helix Retail Polska Sp. z o.o.",
    "nazwaSkrocona": "Helix Retail Polska",
    "formaPrawna": "Sp. z o.o.",
    "status": "AKTYWNY",
    "dataRejestracji": "2019-01-10",
    "siedziba": "Olsztyn",
    "adres": "10-687 Olsztyn, ul Jarzębinowa 157 m.16",
    "pkd": "62.02.Z",
    "kapitalZakladowy": "10000 PLN",
    "reprezentacja": "dwóch członków zarządu łącznie"
  },
  {
    "numerKRS": "9335390058",
    "nip": "6639792551",
    "regon": "561547315",
    "nazwa": "Vistula Data Hub Solutions sp z oo",
    "nazwaSkrocona": "VISTULA DATA HUB SOLUTIONS",
    "formaPrawna": "sp z oo",
    "status": "AKTYWNY",
    "dataRejestracji": "2022-02-27",
    "siedziba": "Wrocław",
    "adres": "ul Kazimierza Wielkiego 21, 50-101 Wrocław",
    "pkd": "64.19.Z",
    "kapitalZakladowy": "100000 PLN",
    "reprezentacja": "każdy członek zarządu samodzielnie"
  },
  {
    "numerKRS": "3042763628",
    "nip": "9530969067",
    "regon": "144471893",
    "nazwa": "Helix Retail Solutions sp z oo",
    "nazwaSkrocona": "Helix Retail Solutions",
    "formaPrawna": "sp z oo",
    "status": "AKTYWNY",
    "dataRejestracji": "2019-02-25",
    "siedziba": "Gdynia",
    "adres": "81-350 Gdynia, Portowa 32",
    "pkd": "47.91.Z",
    "kapitalZakladowy": "5000 PLN",
    "reprezentacja": "każdy członek zarządu samodzielnie"
  },
  {
    "numerKRS": "7041309091",
    "nip": "2542041231",
    "regon": "538602826",
    "nazwa": "Nova Systems Gruop sp z oo",
    "nazwaSkrocona": "NOVA SYSTEMS GROUP",
    "formaPrawna": "sp z oo",
    "status": "AKTYWNY",
    "dataRejestracji": "2020-03-25",
    "siedziba": "Gdynia",
    "adres": "81-350 Gdynia, Portowa 132",
    "pkd": "63.11.Z",
    "kapitalZakladowy": "100000 PLN",
    "reprezentacja": "każdy członek zarządu samodzielnie"
  },
  {
    "numerKRS": "2611890034",
    "nip": "2867202009",
    "regon": "686163070",
    "nazwa": "Altair Finance Polska sp. z o..o",
    "nazwaSkrocona": "Altair Finance Polska",
    "formaPrawna": "sp. z o.o.",
    "status": "AKTYWNY",
    "dataRejestracji": "2025-04-20",
    "siedziba": "Wrocław",
    "adres": "50-101 Wrocław, ul Kazimierza Wielkiego 77 m.6",
    "pkd": "62.02.Z",
    "kapitalZakladowy": "10000 PLN",
    "reprezentacja": "każdy członek zarządu samodzielnie"
  },
  {
    "numerKRS": "5461719281",
    "nip": "3442252160",
    "regon": "707443602",
    "nazwa": "Orbis Retail Solutions Group Sp. z o.o.",
    "nazwaSkrocona": "Orbis Retail Solutions Group",
    "formaPrawna": "Sp. z o.o.",
    "status": "W TRAKCIE LIKWIDACJI",
    "dataRejestracji": "2025-10-27",
    "siedziba": "Lublin",
    "adres": "20-819 Lublin, Topolowa 168",
    "pkd": "64.19.Z",
    "kapitalZakladowy": "1200000 PLN",
    "reprezentacja": "każdy członek zarządu samodzielnie"
  },
  {
    "numerKRS": "2686498647",
    "nip": "0884474083",
    "regon": "868623760",
    "nazwa": "Helix Retail Solutions spółka akcyjna",
    "nazwaSkrocona": "HELIX RETAIL SOLUTIONS",
    "formaPrawna": "spółka akcyjna",
    "status": "AKTYWNY",
    "dataRejestracji": "2025-01-17",
    "siedziba": "Rzeszów",
    "adres": "ul. 3 Maja 171, 35-001 Rzeszów",
    "pkd": "62.02.Z",
    "kapitalZakladowy": "10000 PLN",
    "reprezentacja": "likwidator samodzielnie"
  },
  {
    "numerKRS": "3300008863",
    "nip": "8899114160",
    "regon": "467391900",
    "nazwa": "Nebula Analytics Holding spółka akcyjna",
    "nazwaSkrocona": "Nebula Analytics Holding",
    "formaPrawna": "spółka akcyjna",
    "status": "AKTYWNY",
    "dataRejestracji": "2018-01-20",
    "siedziba": "Wrocław",
    "adres": "ulica Kazimierza Wielkiego 176/5, 50-101 Wrocław",
    "pkd": "63.11.Z",
    "kapitalZakladowy": "50000 PLN",
    "reprezentacja": "likwidator samodzielnie"
  },
  {
    "numerKRS": "2942034015",
    "nip": "6999449466",
    "regon": "353466075",
    "nazwa": "Vistula Data HubT ech SP Z O O",
    "nazwaSkrocona": "Vistula Data Hub Tech",
    "formaPrawna": "SP Z O O",
    "status": "AKTYWNY",
    "dataRejestracji": "2022-12-11",
    "siedziba": "Lublin",
    "adres": "ul. Topolowa 170/21, 20-819 Lublin",
    "pkd": "62.01.Z",
    "kapitalZakladowy": "10000 PLN",
    "reprezentacja": "dwóch członków zarządu łącznie"
  },
  {
    "numerKRS": "1255904610",
    "nip": "0012838271",
    "regon": "079230466",
    "nazwa": "Vistula Data Hub Polska sp z oo",
    "nazwaSkrocona": "Vistula Dtaa Hub Polska",
    "formaPrawna": "sp z oo",
    "status": "AKTYWNY",
    "dataRejestracji": "2020-08-14",
    "siedziba": "Lublin",
    "adres": "ul. Topolowa 144/18, 20-819 Lublin",
    "pkd": "64.19.Z",
    "kapitalZakladowy": "50000 PLN",
    "reprezentacja": "dwóch członków zarządu łącznie"
  },
  {
    "numerKRS": "6176822512",
    "nip": "5622419768",
    "regon": "726708666",
    "nazwa": "Orbis Retail Solutions Holding SP Z O O",
    "nazwaSkrocona": "Orbis Retail Solutions Holding",
    "formaPrawna": "SP Z O O",
    "status": "AKTYWNY",
    "dataRejestracji": "2018-05-24",
    "siedziba": "Olsztyn",
    "adres": "10-687 Olsztyn, Jarzębinowa 80",
    "pkd": "64.19.Z",
    "kapitalZakladowy": "100000 PLN",
    "reprezentacja": "likwidator samodzielnie"
  },
  {
    "numerKRS": "1197388182",
    "nip": "4882188496",
    "regon": "730634359",
    "nazwa": "Altair Finance Holding spółka z ograniczoną odpowiedzialnością",
    "nazwaSkrocona": "Altair Finance Holdnig",
    "formaPrawna": "spółka z ograniczoną odpowiedzialnością",
    "status": "W TRAKCIE LIKWIDACJI",
    "dataRejestracji": "2024-01-27",
    "siedziba": "Bydgoszcz",
    "adres": "ul. Bałtycka 5/22, 85-707 Bydgoszcz",
    "pkd": "62.01.Z",
    "kapitalZakladowy": "10000 PLN",
    "reprezentacja": "każdy członek zarządu samodzielnie"
  },
  {
    "numerKRS": "0347131719",
    "nip": "0841947855",
    "regon": "786016259",
    "nazwa": "Baltic Med Supply Polska spółka akcyjna",
    "nazwaSkrocona": "BALTIC MED SUPPLY POLSKA",
    "formaPrawna": "spółka akcyjna",
    "status": "AKTYWNY",
    "dataRejestracji": "2023-09-06",
    "siedziba": "Rzeszów",
    "adres": "ulica 3 Maja 160/2, 35-001 Rzeszów",
    "pkd": "62.02.Z",
    "kapitalZakladowy": "5000 PLN",
    "reprezentacja": "dwóch członków zarządu łącznie"
  },
  {
    "numerKRS": "8197223996",
    "nip": "0768102480",
    "regon": "477183753",
    "nazwa": "Meridian Trade Polska SP Z O O",
    "nazwaSkrocona": "Meridian Trade Polska",
    "formaPrawna": "SP Z O O",
    "status": "AKTYWNY",
    "dataRejestracji": "2025-05-13",
    "siedziba": "Olsztyn",
    "adres": "ul Jarzębinowa 120, 10-687 Olsztyn",
    "pkd": "62.01.Z",
    "kapitalZakladowy": "5000 PLN",
    "reprezentacja": "dwóch członków zarządu łącznie"
  },
  {
    "numerKRS": "6107033508",
    "nip": "2484813004",
    "regon": "424319839",
    "nazwa": "Baltic Med Supply Services spółka akcyjna",
    "nazwaSkrocona": "Baltic Med Supply Services",
    "formaPrawna": "spółka akcyjna",
    "status": "AKTYWNY",
    "dataRejestracji": "2023-04-02",
    "siedziba": "Bydgoszcz",
    "adres": "ul. Bałtycka 23, 85-707 Bydgoszcz",
    "pkd": "62.02.Z",
    "kapitalZakladowy": "50000 PLN",
    "reprezentacja": "każdy członek zarządu samodzielnie"
  },
  {
    "numerKRS": "1476427896",
    "nip": "8177512395",
    "regon": "157385512",
    "nazwa": "Baltic Med Supply Polska spółka z ograniczoną odpowiedzialnością",
    "nazwaSkrocona": "BALTIC MED SUPPLY POLSKA",
    "formaPrawna": "spółka z ograniczoną odpowiedzialnością",
    "status": "AKTYWNY",
    "dataRejestracji": "2024-11-02",
    "siedziba": "Gdynia",
    "adres": "ul Portowa 60, 81-350 Gdynia",
    "pkd": "63.11.Z",
    "kapitalZakladowy": "100000 PLN",
    "reprezentacja": "każdy członek zarządu samodzielnie"
  },
  {
    "numerKRS": "0871564783",
    "nip": "0274148572",
    "regon": "703175438",
    "nazwa": "Polaris Medical Polska sp. z o.o.",
    "nazwaSkrocona": "Polaris Medical Polska",
    "formaPrawna": "sp. z o.o.",
    "status": "AKTYWNY",
    "dataRejestracji": "2020-08-03",
    "siedziba": "Bydgoszcz",
    "adres": "ul Bałtycka 10, 85-707 Bydgoszcz",
    "pkd": "46.46.Z",
    "kapitalZakladowy": "50000 PLN",
    "reprezentacja": "każdy członek zarządu samodzielnie"
  },
  {
    "numerKRS": "6932055340",
    "nip": "1597640535",
    "regon": "508927396",
    "nazwa": "Nebula Analytics Holding SP Z O O",
    "nazwaSkrocona": "Nebula Analytics Holding",
    "formaPrawna": "SP Z O O",
    "status": "AKTYWNY",
    "dataRejestracji": "2020-03-21",
    "siedziba": "Katowice",
    "adres": "ul. Chorzowska 122/14, 40-121 Katowice",
    "pkd": "62.01.Z",
    "kapitalZakladowy": "5000 PLN",
    "reprezentacja": "każdy członek zarządu samodzielnie"
  },
  {
    "numerKRS": "6983052169",
    "nip": "8014264710",
    "regon": "039220269",
    "nazwa": "Vistula Data Hub Polska SP Z O O",
    "nazwaSkrocona": "VISTULA DATA HUB POLSKA",
    "formaPrawna": "SP Z O O",
    "status": "W TRAKCIE LIKWIDACJI",
    "dataRejestracji": "2021-02-28",
    "siedziba": "Poznań",
    "adres": "60-126 Poznań, ul Głogowska 41 m.18",
    "pkd": "46.46.Z",
    "kapitalZakladowy": "1200000 PLN",
    "reprezentacja": "dwóch członków zarządu łącznie"
  },
  {
    "numerKRS": "5193932727",
    "nip": "0496026676",
    "regon": "281291635",
    "nazwa": "Vistula Data Hub Solutions SP Z O O",
    "nazwaSkrocona": "Vistula Data Hub Solutions",
    "formaPrawna": "SP Z O O",
    "status": "AKTYWNY",
    "dataRejestracji": "2018-09-01",
    "siedziba": "Gdynia",
    "adres": "ul Portowa 67, 81-350 Gdynia",
    "pkd": "64.19.Z",
    "kapitalZakladowy": "5000 PLN",
    "reprezentacja": "likwidator samodzielnie"
  },
  {
    "numerKRS": "3332023510",
    "nip": "4503698884",
    "regon": "255501935",
    "nazwa": "Nova Systems Group S.A.",
    "nazwaSkrocona": "NOVA SYSTEMS GROUP",
    "formaPrawna": "S.A.",
    "status": "AKTYWNY",
    "dataRejestracji": "2024-06-28",
    "siedziba": "Katowice",
    "adres": "ulica Chorzowska 147/19, 40-121 Katowice",
    "pkd": "63.11.Z",
    "kapitalZakladowy": "1200000 PLN",
    "reprezentacja": "każdy członek zarządu samodzielnie"
  },
  {
    "numerKRS": "1937591922",
    "nip": "2647528646",
    "regon": "671317536",
    "nazwa": "Nebula Analytics Services Sp. z o.o.",
    "nazwaSkrocona": "NEBULA ANALYTICS SERVICES",
    "formaPrawna": "Sp. z o.o.",
    "status": "AKTYWNY",
    "dataRejestracji": "2023-02-09",
    "siedziba": "Poznań",
    "adres": "ul. Głogowska 41, 60-126 Poznań",
    "pkd": "64.19.Z",
    "kapitalZakladowy": "10000 PLN",
    "reprezentacja": "każdy członek zarządu samodzielnie"
  },
  {
    "numerKRS": "8834581920",
    "nip": "3332998651",
    "regon": "487706769",
    "nazwa": "Altair Finance Group spółka z ograniczoną odpowiedzialnością",
    "nazwaSkrocona": "ALTAIR FINANCE GROUP",
    "formaPrawna": "spółka z ograniczoną odpowiedzialnością",
    "status": "AKTYWNY",
    "dataRejestracji": "2018-12-17",
    "siedziba": "Wrocław",
    "adres": "50-101 Wrocław, ul Kazimierza Wielkiego 155 m.12",
    "pkd": "62.01.Z",
    "kapitalZakladowy": "100000 PLN",
    "reprezentacja": "każdy członek zarządu samodzielnie"
  },
  {
    "numerKRS": "2472863942",
    "nip": "9290096627",
    "regon": "012234149",
    "nazwa": "Baltic Med Supply Solutions sp z oo",
    "nazwaSkrocona": "Baltic Med Supply Solutions",
    "formaPrawna": "sp z oo",
    "status": "W TRAKCIE LIKWIDACJI",
    "dataRejestracji": "2020-03-06",
    "siedziba": "Bydgoszcz",
    "adres": "85-707 Bydgoszcz, ul Bałtycka 47 m.1",
    "pkd": "62.01.Z",
    "kapitalZakladowy": "5000 PLN",
    "reprezentacja": "każdy członek zarządu samodzielnie"
  },
  {
    "numerKRS": "7626438500",
    "nip": "7623133610",
    "regon": "953723461",
    "nazwa": "Baltic Med Supply Tech spółka z ograniczoną odpowiedzialnością",
    "nazwaSkrocona": "Baltic Med Supply Tech",
    "formaPrawna": "spółka z ograniczoną odpowiedzialnością",
    "status": "AKTYWNY",
    "dataRejestracji": "2021-05-20",
    "siedziba": "Gdynia",
    "adres": "81-350 Gdynia, Portowa 103",
    "pkd": "46.46.Z",
    "kapitalZakladowy": "1200000 PLN",
    "reprezentacja": "każdy członek zarządu samodzielnie"
  },
  {
    "numerKRS": "2483744417",
    "nip": "9479025485",
    "regon": "234565386",
    "nazwa": "Orbis Retail Solutions Holding spółka z ograniczoną odpowiedzialnością",
    "nazwaSkrocona": "ORBIS RETAIL SOLUTIONS HOLDING",
    "formaPrawna": "spółka z ograniczoną odpowiedzialnością",
    "status": "W TRAKCIE LIKWIDACJI",
    "dataRejestracji": "2018-05-23",
    "siedziba": "Wrocław",
    "adres": "50-101 Wrocław, ul Kazimierza Wielkiego 159 m.7",
    "pkd": "46.46.Z",
    "kapitalZakladowy": "10000 PLN",
    "reprezentacja": "likwidator samodzielnie"
  },
  {
    "numerKRS": "3599009378",
    "nip": "3788443706",
    "regon": "146047614",
    "nazwa": "Orbis Retail Solutions Polsk aSp. z o.o.",
    "nazwaSkrocona": "ORBIS RETAIL SOLUTIONS POLSKA",
    "formaPrawna": "Sp. z o.o.",
    "status": "AKTYWNY",
    "dataRejestracji": "2022-07-28",
    "siedziba": "Gdynia",
    "adres": "81-350 Gdynia, ul Portowa 124 m.9",
    "pkd": "46.46.Z",
    "kapitalZakladowy": "100000 PLN",
    "reprezentacja": "każdy członek zarządu samodzielnie"
  },
  {
    "numerKRS": "8450786043",
    "nip": "4698330677",
    "regon": "566050337",
    "nazwa": "Orbis Retail Solutions Solutions spółka akcyjna",
    "nazwaSkrocona": "Orbis Retail Solutions Solutions",
    "formaPrawna": "spółka akcyjna",
    "status": "W TRAKCIE LIKWIDACJI",
    "dataRejestracji": "2018-07-16",
    "siedziba": "Warszawa",
    "adres": "ul. Srebrna 39, 00-810 Warszawa",
    "pkd": "63.11.Z",
    "kapitalZakladowy": "100000 PLN",
    "reprezentacja": "każdy członek zarządu samodzielnie"
  },
  {
    "numerKRS": "7048618670",
    "nip": "0739928919",
    "regon": "663201629",
    "nazwa": "Orbis Retail Solutions Group SA",
    "nazwaSkrocona": "Orbis Retail Solutions Group",
    "formaPrawna": "SA",
    "status": "AKTYWNY",
    "dataRejestracji": "2024-12-11",
    "siedziba": "Warszawa",
    "adres": "ul. Srebrna 172/19, 00-810 Warszawa",
    "pkd": "46.46.Z",
    "kapitalZakladowy": "100000 PLN",
    "reprezentacja": "każdy członek zarządu samodzielnie"
  },
  {
    "numerKRS": "5490145996",
    "nip": "7305498243",
    "regon": "706921958",
    "nazwa": "Nova Systems Polska sp. z o.o.",
    "nazwaSkrocona": "Nova Systems Polska",
    "formaPrawna": "sp. z o.o.",
    "status": "AKTYWNY",
    "dataRejestracji": "2024-11-28",
    "siedziba": "Olsztyn",
    "adres": "10-687 Olsztyn, ul Jarzębinowa 179 m.22",
    "pkd": "63.11.Z",
    "kapitalZakladowy": "10000 PLN",
    "reprezentacja": "likwidator samodzielnie"
  },
  {
    "numerKRS": "8081726282",
    "nip": "0728895927",
    "regon": "968244850",
    "nazwa": "Polaris Medical Polska SP Z O O",
    "nazwaSkrocona": "Ploaris Medical Polska",
    "formaPrawna": "SP Z O O",
    "status": "AKTYWNY",
    "dataRejestracji": "2024-04-22",
    "siedziba": "Bydgoszcz",
    "adres": "85-707 Bydgoszcz, ul Bałtycka 106 m.2",
    "pkd": "47.91.Z",
    "kapitalZakladowy": "50000 PLN",
    "reprezentacja": "każdy członek zarządu samodzielnie"
  },
  {
    "numerKRS": "3690912375",
    "nip": "3967024365",
    "regon": "302849760",
    "nazwa": "Altair Finance Group Sp. z .oo.",
    "nazwaSkrocona": "ALTAIR FINANCE GROUP",
    "formaPrawna": "Sp. z o.o.",
    "status": "AKTYWNY",
    "dataRejestracji": "2021-09-12",
    "siedziba": "Poznań",
    "adres": "60-126 Poznań, ul Głogowska 170 m.5",
    "pkd": "64.19.Z",
    "kapitalZakladowy": "100000 PLN",
    "reprezentacja": "dwóch członków zarządu łącznie"
  },
  {
    "numerKRS": "9722042986",
    "nip": "6179962356",
    "regon": "226992066",
    "nazwa": "Baltic Med Supply Group Sp. z o.o.",
    "nazwaSkrocona": "Baltic Med Supply Group",
    "formaPrawna": "Sp. z o.o.",
    "status": "AKTYWNY",
    "dataRejestracji": "2021-02-11",
    "siedziba": "Katowice",
    "adres": "ul. Chorzowska 105, 40-121 Katowice",
    "pkd": "63.11.Z",
    "kapitalZakladowy": "1200000 PLN",
    "reprezentacja": "likwidator samodzielnie"
  },
  {
    "numerKRS": "1430491341",
    "nip": "2099865642",
    "regon": "038975287",
    "nazwa": "Polaris Medical Services SP Z O O",
    "nazwaSkrocona": "POLARIS MEDICAL SERVICES",
    "formaPrawna": "SP Z O O",
    "status": "AKTYWNY",
    "dataRejestracji": "2023-10-23",
    "siedziba": "Warszawa",
    "adres": "ulica Srebrna 168/23, 00-810 Warszawa",
    "pkd": "46.46.Z",
    "kapitalZakladowy": "5000 PLN",
    "reprezentacja": "likwidator samodzielnie"
  },
  {
    "numerKRS": "8056820175",
    "nip": "9572404347",
    "regon": "307966186",
    "nazwa": "Meridian Trade Group SA",
    "nazwaSkrocona": "Meridian Trade Gropu",
    "formaPrawna": "SA",
    "status": "AKTYWNY",
    "dataRejestracji": "2018-03-23",
    "siedziba": "Rzeszów",
    "adres": "35-001 Rzeszów, ul 3 Maja 67 m.20",
    "pkd": "63.11.Z",
    "kapitalZakladowy": "1200000 PLN",
    "reprezentacja": "likwidator samodzielnie"
  },
  {
    "numerKRS": "4760786235",
    "nip": "0851732895",
    "regon": "107651917",
    "nazwa": "Polaris Medical Holding spółka z ograniczoną odpowiedzialnością",
    "nazwaSkrocona": "Polaris Medical Holding",
    "formaPrawna": "spółka z ograniczoną odpowiedzialnością",
    "status": "AKTYWNY",
    "dataRejestracji": "2024-01-21",
    "siedziba": "Poznań",
    "adres": "60-126 Poznań, Głogowska 80",
    "pkd": "62.01.Z",
    "kapitalZakladowy": "5000 PLN",
    "reprezentacja": "każdy członek zarządu samodzielnie"
  },
  {
    "numerKRS": "0396620385",
    "nip": "2652951646",
    "regon": "886407880",
    "nazwa": "Helix Retail Group SP Z O O",
    "nazwaSkrocona": "Helix Retail Group",
    "formaPrawna": "SP Z O O",
    "status": "AKTYWNY",
    "dataRejestracji": "2024-03-07",
    "siedziba": "Olsztyn",
    "adres": "ul. Jarzębinowa 155/23, 10-687 Olsztyn",
    "pkd": "46.46.Z",
    "kapitalZakladowy": "1200000 PLN",
    "reprezentacja": "dwóch członków zarządu łącznie"
  },
  {
    "numerKRS": "9918431132",
    "nip": "8052632119",
    "regon": "661158485",
    "nazwa": "Amber Tech Group spółka z ograniczoną odpowiedzialnością",
    "nazwaSkrocona": "Amber Tech Group",
    "formaPrawna": "spółka z ograniczoną odpowiedzialnością",
    "status": "AKTYWNY",
    "dataRejestracji": "2019-05-13",
    "siedziba": "Katowice",
    "adres": "ulica Chorzowska 124/2, 40-121 Katowice",
    "pkd": "62.02.Z",
    "kapitalZakladowy": "1200000 PLN",
    "reprezentacja": "likwidator samodzielnie"
  },
  {
    "numerKRS": "2618402578",
    "nip": "6306636050",
    "regon": "703686050",
    "nazwa": "Nebula Analytics Holding spółka z ograniczoną odpowiedzialnością",
    "nazwaSkrocona": "NEBULA ANALYTICS HOLDING",
    "formaPrawna": "spółka z ograniczoną odpowiedzialnością",
    "status": "AKTYWNY",
    "dataRejestracji": "2025-12-20",
    "siedziba": "Gdynia",
    "adres": "81-350 Gdynia, ul Portowa 180 m.13",
    "pkd": "46.46.Z",
    "kapitalZakladowy": "5000 PLN",
    "reprezentacja": "likwidator samodzielnie"
  },
  {
    "numerKRS": "0548944538",
    "nip": "5583445662",
    "regon": "118081896",
    "nazwa": "Altair Finance Tech sp. z o.o.",
    "nazwaSkrocona": "Altair Finance Tech",
    "formaPrawna": "sp. z o.o.",
    "status": "AKTYWNY",
    "dataRejestracji": "2025-10-16",
    "siedziba": "Wrocław",
    "adres": "ul. Kazimierza Wielkiego 76/9, 50-101 Wrocław",
    "pkd": "47.91.Z",
    "kapitalZakladowy": "100000 PLN",
    "reprezentacja": "dwóch członków zarządu łącznie"
  },
  {
    "numerKRS": "5158501530",
    "nip": "0587905224",
    "regon": "173167156",
    "nazwa": "Meridian Trade Services sp. z o.o.",
    "nazwaSkrocona": "MERIDIAN TRADE SERVICES",
    "formaPrawna": "sp. z o.o.",
    "status": "W TRAKCIE LIKWIDACJI",
    "dataRejestracji": "2022-12-13",
    "siedziba": "Wrocław",
    "adres": "ul Kazimierza Wielkiego 164, 50-101 Wrocław",
    "pkd": "46.46.Z",
    "kapitalZakladowy": "100000 PLN",
    "reprezentacja": "dwóch członków zarządu łącznie"
  },
  {
    "numerKRS": "7718430192",
    "nip": "2973239644",
    "regon": "209567333",
    "nazwa": "Polaris Medcial Polska sp. z o.o.",
    "nazwaSkrocona": "POLARIS MEDICAL POLSKA",
    "formaPrawna": "sp. z o.o.",
    "status": "W TRAKCIE LIKWIDACJI",
    "dataRejestracji": "2018-02-14",
    "siedziba": "Kraków",
    "adres": "ulica Konopnickiej 141/12, 30-302 Kraków",
    "pkd": "46.46.Z",
    "kapitalZakladowy": "10000 PLN",
    "reprezentacja": "każdy członek zarządu samodzielnie"
  },
  {
    "numerKRS": "4526075699",
    "nip": "4332262277",
    "regon": "913831006",
    "nazwa": "Vistula Data Hub Holding S.A.",
    "nazwaSkrocona": "Vistula Data Hub Holding",
    "formaPrawna": "S.A.",
    "status": "W TRAKCIE LIKWIDACJI",
    "dataRejestracji": "2022-03-21",
    "siedziba": "Rzeszów",
    "adres": "35-001 Rzeszów, ul 3 Maja 3 m.16",
    "pkd": "62.02.Z",
    "kapitalZakladowy": "5000 PLN",
    "reprezentacja": "likwidator samodzielnie"
  },
  {
    "numerKRS": "6200363856",
    "nip": "7931839979",
    "regon": "461497459",
    "nazwa": "Orbis Retail Solutions Holding spółka z ograniczoną odpowiedzialnością",
    "nazwaSkrocona": "Orbis Retail Solutions Holding",
    "formaPrawna": "spółka z ograniczoną odpowiedzialnością",
    "status": "AKTYWNY",
    "dataRejestracji": "2022-10-23",
    "siedziba": "Bydgoszcz",
    "adres": "ul Bałtycka 110, 85-707 Bydgoszcz",
    "pkd": "62.01.Z",
    "kapitalZakladowy": "5000 PLN",
    "reprezentacja": "likwidator samodzielnie"
  },
  {
    "numerKRS": "1212898115",
    "nip": "2762239847",
    "regon": "948534001",
    "nazwa": "Nova Systems Solutions sp z oo",
    "nazwaSkrocona": "NOVA SYSTEMS SOLUTIONS",
    "formaPrawna": "sp z oo",
    "status": "W TRAKCIE LIKWIDACJI",
    "dataRejestracji": "2018-07-23",
    "siedziba": "Olsztyn",
    "adres": "ul. Jarzębinowa 33, 10-687 Olsztyn",
    "pkd": "64.19.Z",
    "kapitalZakladowy": "10000 PLN",
    "reprezentacja": "likwidator samodzielnie"
  },
  {
    "numerKRS": "4963830972",
    "nip": "1662016555",
    "regon": "361080926",
    "nazwa": "Helix Retail Services SP Z O O",
    "nazwaSkrocona": "HELIX RETAIL SERVICES",
    "formaPrawna": "SP Z O O",
    "status": "AKTYWNY",
    "dataRejestracji": "2025-11-17",
    "siedziba": "Kraków",
    "adres": "30-302 Kraków, ul Konopnickiej 7 m.11",
    "pkd": "47.91.Z",
    "kapitalZakladowy": "50000 PLN",
    "reprezentacja": "dwóch członków zarządu łącznie"
  },
  {
    "numerKRS": "0516654512",
    "nip": "4023386860",
    "regon": "244418997",
    "nazwa": "Meridian Trade Solutions S.A.",
    "nazwaSkrocona": "Meridian Trade Solutions",
    "formaPrawna": "S.A.",
    "status": "W TRAKCIE LIKWIDACJI",
    "dataRejestracji": "2021-01-20",
    "siedziba": "Wrocław",
    "adres": "50-101 Wrocław, ul Kazimierza Wielkiego 87 m.26",
    "pkd": "64.19.Z",
    "kapitalZakladowy": "5000 PLN",
    "reprezentacja": "każdy członek zarządu samodzielnie"
  },
  {
    "numerKRS": "4135694804",
    "nip": "0957394059",
    "regon": "507356748",
    "nazwa": "Altair Finance Holding SA",
    "nazwaSkrocona": "Altair Finance Holding",
    "formaPrawna": "SA",
    "status": "AKTYWNY",
    "dataRejestracji": "2022-05-05",
    "siedziba": "Rzeszów",
    "adres": "ul 3 Maja 125, 35-001 Rzeszów",
    "pkd": "62.02.Z",
    "kapitalZakladowy": "10000 PLN",
    "reprezentacja": "każdy członek zarządu samodzielnie"
  }
]